CryptoTrackerpy/__init__.py
CryptoTrackerpy/tracker.py
CryptoTrackerr-0.0.2.dist-info/METADATA
CryptoTrackerr-0.0.2.dist-info/WHEEL
CryptoTrackerr-0.0.2.dist-info/top_level.txt
CryptoTrackerr-0.0.2.dist-info/RECORD
